opentak/__init__.py
opentak/clustering.py
opentak/dendrogram_utils.py
opentak/generation_cohort_tak.py
opentak/logger.py
opentak/preprocessing.py
opentak/py.typed
opentak/visualization.py
opentak/tak_theme/__init__.py
opentak/tak_theme/_colors.py
opentak/tak_theme/_theme.py
opentak/tak_theme/_utils.py
opentak/tak_theme/mpl_tak.mplstyle
opentak/tak_theme/palettes.py
opentak/tak_theme/py.typed
opentak/utils_events/__init__.py
opentak/utils_events/checks.py
opentak/utils_events/preprocessing.py
opentak/utils_events/utils.py
opentak-0.1.0.dist-info/METADATA
opentak-0.1.0.dist-info/WHEEL
opentak-0.1.0.dist-info/licenses/LICENSE
opentak-0.1.0.dist-info/RECORD
