Metadata-Version: 2.4
Name: opentak
Version: 0.1.0
Summary: TODO
Project-URL: Homepage, https://heva-io.github.io/opentak/latest/
Project-URL: Documentation, https://heva-io.github.io/opentak/latest/
Project-URL: Repository, https://github.com/heva-io/opentak
Project-URL: Issues, https://github.com/heva-io/opentak/issues
Author-email: Marie-Ange RASENDRA <marie-ange.rasendra@heva-data.com>, Lilian SFEIR <lilian.sfeir@heva-data.com>, Jules CHASSETUILLIER <jules.chassetuillier@heva-data.com>, Quentin FLEURENT-NAMBOT <quentin.fleurent-nambot@heva-data.com>
License-Expression: MPL-2.0
License-File: LICENSE
Requires-Python: <4,>=3.10
Requires-Dist: coloraide>=5.1
Requires-Dist: kaleido<2,>=1.0.0
Requires-Dist: matplotlib-stubs>=0.3.3
Requires-Dist: more-itertools<9.0.0,>=8.7.0
Requires-Dist: nbformat>=5.10.4
Requires-Dist: numpy<3,>=2.2.2
Requires-Dist: pandas<3,>=2.2.1
Requires-Dist: pillow>=11.3.0
Requires-Dist: plotly<7,>=6.1.0
Requires-Dist: scikit-learn<2.0.0,>=1.0.2
Requires-Dist: scipy<2.0.0,>1.3.1
Requires-Dist: webcolors>=24.11.1
